pipecapacity/__init__.py
pipecapacity/__main__.py
pipecapacity/data_table.py
pipecapacity/dropdown.py
pipecapacity/flask_app.py
pipecapacity/html_layout.py
pipecapacity/pipe_capacity.py
pipecapacity/plt_children.py
pipecapacity/textarea_with_submit.py
pipecapacity/common/ApplicationManager.py
pipecapacity/common/MaterialProperties.py
pipecapacity/common/PipeCapacity.py
pipecapacity/common/PipeSizing.py
pipecapacity/common/data.py
pipecapacity/common/pipe_components.py
pipecapacity/common/temperatureDerating.py
pipecapacity/common/update_deep.py
pipecapacity/common/visualization.py
pipecapacity/common/ymlInput.py
pipecapacity/custom/ASMEMethods.py
pipecapacity/custom/MaterialProperties.py
pipecapacity/custom/PipeCapacity.py
pipecapacity/custom/PipeSizing.py
pipecapacity/custom/plotCustom.py
pipecapacity/custom/plotDefault.py
pipecapacity/custom/saveData.py
pipecapacity/custom/temperatureDerating.py
pipecapacity/custom/API_RP_2RD/APIRP2RD_Methods.py
pipecapacity/custom/API_STD_2RD/APISTD2RDMethods.py
pipecapacity/custom/API_STD_2RD/Summary.py
pipecapacity/custom/API_STD_2RD/extractData.py
pipecapacity/custom/API_STD_2RD/fileList.py
pipecapacity/custom/API_STD_2RD/temperatureDerating.py
pipecapacity/custom/API_STD_2RD/BurstPressure/APISTD2RD.py
pipecapacity/custom/API_STD_2RD/BurstPressure/APISTD2RDMethods.py
pipecapacity/custom/API_STD_2RD/BurstPressure/temperatureDerating.py
pipecapacity/custom/API_STD_2RD/BurstPressure/dataManager/__init__.py
pipecapacity/custom/API_STD_2RD/BurstPressure/dataManager/checkPythonEnvironment.py
pipecapacity/custom/API_STD_2RD/BurstPressure/dataManager/customUpdate.py
pipecapacity/custom/API_STD_2RD/BurstPressure/dataManager/loadConfiguration.py
pipecapacity/custom/API_STD_2RD/BurstPressure/dataManager/ymlInput.py
pipecapacity/custom/API_STD_2RD/BurstPressure/logs/__init__.py
pipecapacity/custom/API_STD_2RD/BurstPressure/logs/setLogging.py
pipecapacity/custom/API_STD_2RD/BurstPressure/results/__init__.py
pipecapacity-0.1.0.dist-info/LICENSE
pipecapacity-0.1.0.dist-info/METADATA
pipecapacity-0.1.0.dist-info/WHEEL
pipecapacity-0.1.0.dist-info/entry_points.txt
pipecapacity-0.1.0.dist-info/top_level.txt
pipecapacity-0.1.0.dist-info/RECORD
