Metadata-Version: 2.1
Name: pipecapacity
Version: 0.1.0
Summary: Pipe Capacity usnig code calculations
Author-email: Vamsee Achanta <vamsee.achanta@aceengineer.com>
License: MIT License
Project-URL: repository, https://github.com/vamseeachanta/pipecapacity
Project-URL: documentation, https://github.com/vamseeachanta/pipecapacity/blob/main/README.md
Keywords: pipe capacity,pipe strength,code calculations,code evaluations,pipe utilization,capacity utilization,pressure calculations
Classifier: License :: OSI Approved :: MIT License
Classifier: Programming Language :: Python
Classifier: Programming Language :: Python :: 3
Requires-Python: >=3.7
License-File: LICENSE
Requires-Dist: pyyaml
Requires-Dist: plotly
Requires-Dist: webcolors
Requires-Dist: flask-wtf
Requires-Dist: flask-httpauth
Requires-Dist: flask-restful
Requires-Dist: urllib3
Requires-Dist: tomli ; python_version < "3.11"
Provides-Extra: build
Requires-Dist: build ; extra == 'build'
Requires-Dist: twine ; extra == 'build'
Provides-Extra: dev
Requires-Dist: black ; extra == 'dev'
Requires-Dist: bumpver ; extra == 'dev'
Requires-Dist: isort ; extra == 'dev'
Requires-Dist: pytest ; extra == 'dev'
